spampy/__init__.py
spampy/__main__.py
spampy/dataset_downloader.py
spampy/email_processor.py
spampy/spam_classifier.py
spampy/datasets/spamTest.mat
spampy/datasets/spamTrain.mat
spampy/datasets/vocablary.txt
spampy-0.3.1.dist-info/COPYING
spampy-0.3.1.dist-info/LICENSE
spampy-0.3.1.dist-info/METADATA
spampy-0.3.1.dist-info/NOTICE
spampy-0.3.1.dist-info/WHEEL
spampy-0.3.1.dist-info/top_level.txt
spampy-0.3.1.dist-info/RECORD
