Metadata-Version: 2.1
Name: spampy
Version: 0.3.1
Summary: Spam filtering module with Machine Learning using SVM.
Home-page: https://github.com/abdullahselek/spampy
Author: Abdullah Selek
Author-email: abdullahselek@gmail.com
Maintainer: Abdullah Selek
Maintainer-email: abdullahselek@gmail.com
License: MIT License
Download-URL: https://pypi.org/project/spampy/
Keywords: machine learning,spam filter,support vector machine,spam,svm
Platform: Any
Classifier: Intended Audience :: Developers
Classifier: Intended Audience :: Science/Research
Classifier: License :: OSI Approved :: MIT License
Classifier: Operating System :: OS Independent
Classifier: Topic :: Software Development
Classifier: Topic :: Scientific/Engineering
Classifier: Programming Language :: Python
Classifier: Programming Language :: Python :: 3.5
Classifier: Programming Language :: Python :: 3.6
Classifier: Programming Language :: Python :: 3.7
Classifier: Programming Language :: Python :: 3.8
Classifier: Programming Language :: Python :: 3.9
Requires-Python: !=3.0.*, !=3.1.*, !=3.2.*, !=3.3.*, !=3.4.*, <4
Requires-Dist: scikit-learn
Requires-Dist: scipy
Requires-Dist: numpy
Requires-Dist: nltk
Requires-Dist: click
